datapurifier/README.md
datapurifier/__init__.py
datapurifier/dataset.py
datapurifier/decorators.py
datapurifier/ml_utils.py
datapurifier/purify.py
datapurifier/report.py
datapurifier/utils.py
datapurifier/widgets.py
datapurifier/cleaning/__init__.py
datapurifier/cleaning/cleaner.py
datapurifier/cleaning/contractions.py
datapurifier/cleaning/nlpurifier.py
datapurifier/eda/__init__.py
datapurifier/eda/mleda.py
datapurifier/eda/nlpeda.py
datapurifier/models/__init__.py
datapurifier/models/classification.py
datapurifier/preprocessing/__init__.py
datapurifier/preprocessing/cat_encoding.py
datapurifier/preprocessing/contractions.py
datapurifier/preprocessing/encoding.py
datapurifier/preprocessing/mlpurifier.py
datapurifier/preprocessing/nlpurifier.py
datapurifier/preprocessing/scaling.py
datapurifier/preprocessing/data_dict/__init__.py
datapurifier/preprocessing/data_dict/contractions.py
datapurifier/preprocessing/data_dict/emoji.py
datapurifier/preprocessing/data_dict/emoticons.py
data_purifier-0.3.5.dist-info/LICENSE
data_purifier-0.3.5.dist-info/METADATA
data_purifier-0.3.5.dist-info/WHEEL
data_purifier-0.3.5.dist-info/top_level.txt
data_purifier-0.3.5.dist-info/RECORD
