Metadata-Version: 2.1
Name: data-purifier
Version: 0.3.5
Summary: A Python library for Automated Exploratory Data Analysis, Automated Data Cleaning and Automated Data Preprocessing For Machine Learning and Natural Language Processing Applications in Python.
Home-page: https://github.com/Elysian01/Data-Purifier
Author: Abhishek Manilal Gupta
Author-email: abhig0209@gmail.com
License: MIT
Keywords: automated eda exploratory-data-analysis data-cleaning data-preprocessing python jupyter ipython
Platform: UNKNOWN
Classifier: Development Status :: 5 - Production/Stable
Classifier: Topic :: Software Development :: Libraries :: Python Modules
Classifier: License :: OSI Approved :: MIT License
Classifier: Environment :: Console
Classifier: Operating System :: OS Independent
Classifier: Intended Audience :: Science/Research
Classifier: Intended Audience :: Developers
Classifier: Intended Audience :: Financial and Insurance Industry
Classifier: Intended Audience :: Healthcare Industry
Classifier: Topic :: Scientific/Engineering
Classifier: Framework :: IPython
Classifier: Programming Language :: Python :: 3
Classifier: Programming Language :: Python :: 3.6
Classifier: Programming Language :: Python :: 3.7
Classifier: Programming Language :: Python :: 3.8
Classifier: Programming Language :: Python :: 3.9
Requires-Python: >=3.6
Requires-Dist: beautifulsoup4 (>=4.9.3)
Requires-Dist: termcolor (>=1.1.0)
Requires-Dist: joblib
Requires-Dist: scipy (>=1.4.1)
Requires-Dist: pandas (!=1.0.0,!=1.0.1,!=1.0.2,!=1.1.0,>=0.25.3)
Requires-Dist: matplotlib (>=3.2.0)
Requires-Dist: plotly (>=4.14.3)
Requires-Dist: cufflinks (>=0.17.3)
Requires-Dist: confuse (>=1.0.0)
Requires-Dist: jinja2 (>=2.11.1)
Requires-Dist: numpy (>=1.16.0)
Requires-Dist: ipywidgets (==7.6.3)
Requires-Dist: scikit-learn (>=0.24.1)
Requires-Dist: wordcloud (>=1.8.1)
Requires-Dist: textblob (>=0.15.3)
Requires-Dist: tangled-up-in-unicode (>=0.0.6)
Requires-Dist: Unidecode (==1.2.0)
Requires-Dist: unidecode (==1.2.0)
Requires-Dist: requests (>=2.24.0)
Requires-Dist: seaborn (>=0.10.1)
Requires-Dist: spacy (<4.0.0,>=3.0.0)
Provides-Extra: notebook
Requires-Dist: jupyter-client (>=6.0.0) ; extra == 'notebook'
Requires-Dist: jupyter-core (>=4.6.3) ; extra == 'notebook'
Requires-Dist: ipywidgets (>=7.5.1) ; extra == 'notebook'
